Expects/__init__.py
Expects/substrings.py
robotframework_expects-0.4.0.dist-info/METADATA
robotframework_expects-0.4.0.dist-info/WHEEL
robotframework_expects-0.4.0.dist-info/top_level.txt
robotframework_expects-0.4.0.dist-info/RECORD
