Metadata-Version: 2.1
Name: robotframework-expects
Version: 0.4.0
Summary: Train and use expectation detector in Robot Framework tests.
Home-page: https://github.com/mkorpela/robotframework-expects
Author: Mikko Korpela
Author-email: mikko.korpela@gmail.com
License: Apache License, Version 2.0
Keywords: testing
Platform: UNKNOWN
Classifier: Intended Audience :: Developers
Classifier: Natural Language :: English
Classifier: Programming Language :: Python :: 3.6
Classifier: Programming Language :: Python :: 3.7
